kong_control_plane/__init__.py
kong_control_plane/py.typed
kong_control_plane/_jsii/__init__.py
kong_control_plane/_jsii/kong-control-plane@2.0.11.jsii.tgz
kong_control_plane-2.0.11.dist-info/LICENSE
kong_control_plane-2.0.11.dist-info/METADATA
kong_control_plane-2.0.11.dist-info/WHEEL
kong_control_plane-2.0.11.dist-info/top_level.txt
kong_control_plane-2.0.11.dist-info/RECORD
